{
  "slug": "children-who-need-palliative-care",
  "title": "All-Party Parliamentary Group for Children who Need Palliative Care",
  "purpose": "To inform policy which secures the best quality of life and death for the growing number of babies, children and young people with life-limiting or life-threatening conditions. To improve awareness of their needs and to make sure they are understood by those who can help, including government and parliament.",
  "categories": [
    "Health, Medicine & Public Health",
    "Social Care, Welfare & Family Support"
  ],
  "source_url": "https://publications.parliament.uk/pa/cm/cmallparty/260223/children-who-need-palliative-care.htm",
  "secretariat": "Together for Short Lives acts as the group's secretariat.https://www.togetherforshortlives.org.uk/",
  "website": "https://www.togetherforshortlives.org.uk/changing-lives/speaking-up-for-children/policy-advocacy/all-party-parliamentary-group-for-children-who-need-palliative-care",
  "registered_contact_name": "Dame Siobhain McDonagh MP",
  "date_of_most_recent_agm": "2025-11-18 00:00:00",
  "totals": {
    "12m": {
      "monetary": 0.0,
      "inkind": 0.0,
      "combined": 0.0,
      "payment_count": 0,
      "donor_count": 0,
      "mp_count": 0
    },
    "ytd": {
      "monetary": 0.0,
      "inkind": 0.0,
      "combined": 0.0,
      "payment_count": 0,
      "donor_count": 0,
      "mp_count": 0
    },
    "2025": {
      "monetary": 0.0,
      "inkind": 0.0,
      "combined": 0.0,
      "payment_count": 0,
      "donor_count": 0,
      "mp_count": 0
    },
    "2024": {
      "monetary": 0.0,
      "inkind": 0.0,
      "combined": 0.0,
      "payment_count": 0,
      "donor_count": 0,
      "mp_count": 0
    },
    "since_election": {
      "monetary": 0.0,
      "inkind": 0.0,
      "combined": 0.0,
      "payment_count": 0,
      "donor_count": 0,
      "mp_count": 0
    },
    "all_time": {
      "monetary": 0.0,
      "inkind": 0.0,
      "combined": 0.0,
      "payment_count": 0,
      "donor_count": 0,
      "mp_count": 0
    }
  },
  "officers": [
    {
      "appg_slug": "children-who-need-palliative-care",
      "mnis_id": null,
      "name": "Baroness Finlay of Llandaff",
      "canon_name": null,
      "officer_role": "Vice Chair",
      "is_officer": 1,
      "member_type": "lord",
      "last_updated": "2026-02-23 00:00:00",
      "url_source": "https://publications.parliament.uk/pa/cm/cmallparty/260223/children-who-need-palliative-care.htm",
      "removed": null
    },
    {
      "appg_slug": "children-who-need-palliative-care",
      "mnis_id": 193,
      "name": "Dame Siobhain McDonagh",
      "canon_name": "Siobhain McDonagh",
      "officer_role": "Chair & Registered Contact",
      "is_officer": 1,
      "member_type": "mp",
      "last_updated": "2026-02-23 00:00:00",
      "url_source": "https://publications.parliament.uk/pa/cm/cmallparty/260223/children-who-need-palliative-care.htm",
      "removed": null
    },
    {
      "appg_slug": "children-who-need-palliative-care",
      "mnis_id": 4302,
      "name": "Lord Balfe",
      "canon_name": "Lord Balfe",
      "officer_role": "Co-Chair",
      "is_officer": 1,
      "member_type": "lord",
      "last_updated": "2026-02-23 00:00:00",
      "url_source": "https://publications.parliament.uk/pa/cm/cmallparty/260223/children-who-need-palliative-care.htm",
      "removed": null
    },
    {
      "appg_slug": "children-who-need-palliative-care",
      "mnis_id": 4397,
      "name": "Peter Dowd",
      "canon_name": "Peter Dowd",
      "officer_role": "Vice Chair",
      "is_officer": 1,
      "member_type": "mp",
      "last_updated": "2026-02-23 00:00:00",
      "url_source": "https://publications.parliament.uk/pa/cm/cmallparty/260223/children-who-need-palliative-care.htm",
      "removed": null
    }
  ],
  "members": [
    {
      "appg_slug": "children-who-need-palliative-care",
      "mnis_id": null,
      "name": "Baroness Finlay of Llandaff",
      "canon_name": null,
      "officer_role": "Vice Chair",
      "is_officer": 1,
      "member_type": "lord",
      "last_updated": "2026-02-23 00:00:00",
      "url_source": "https://publications.parliament.uk/pa/cm/cmallparty/260223/children-who-need-palliative-care.htm",
      "removed": null
    },
    {
      "appg_slug": "children-who-need-palliative-care",
      "mnis_id": 193,
      "name": "Dame Siobhain McDonagh",
      "canon_name": "Siobhain McDonagh",
      "officer_role": "Chair & Registered Contact",
      "is_officer": 1,
      "member_type": "mp",
      "last_updated": "2026-02-23 00:00:00",
      "url_source": "https://publications.parliament.uk/pa/cm/cmallparty/260223/children-who-need-palliative-care.htm",
      "removed": null
    },
    {
      "appg_slug": "children-who-need-palliative-care",
      "mnis_id": 4302,
      "name": "Lord Balfe",
      "canon_name": "Lord Balfe",
      "officer_role": "Co-Chair",
      "is_officer": 1,
      "member_type": "lord",
      "last_updated": "2026-02-23 00:00:00",
      "url_source": "https://publications.parliament.uk/pa/cm/cmallparty/260223/children-who-need-palliative-care.htm",
      "removed": null
    },
    {
      "appg_slug": "children-who-need-palliative-care",
      "mnis_id": 4397,
      "name": "Peter Dowd",
      "canon_name": "Peter Dowd",
      "officer_role": "Vice Chair",
      "is_officer": 1,
      "member_type": "mp",
      "last_updated": "2026-02-23 00:00:00",
      "url_source": "https://publications.parliament.uk/pa/cm/cmallparty/260223/children-who-need-palliative-care.htm",
      "removed": null
    }
  ],
  "payments": []
}
