{
  "slug": "leasehold-and-commonhold-reform",
  "title": "All-Party Parliamentary Group on Leasehold and Commonhold Reform",
  "purpose": "To consider matters relating to leasehold and commonhold legislation and regulation. Reduce opportunities for exploitation and improve cladding. Review the leasehold property Tribunal as a low-cost forum for disputes and redress including leasehold insurance and service charges which fall outside FCA (Financial Conduct Authority) regulation. Meet with and monitor government departments and publicly funded bodies working on leasehold.",
  "categories": [
    "Housing, Planning & Built Environment"
  ],
  "source_url": "https://publications.parliament.uk/pa/cm/cmallparty/260223/leasehold-and-commonhold-reform.htm",
  "secretariat": "Leasehold Knowledge Partnership acts as the group's secretariat.https://www.leaseholdknowledge.com/",
  "website": "https://www.leaseholdknowledge.com/category/appg/",
  "registered_contact_name": "Justin Madders MP",
  "date_of_most_recent_agm": "2025-11-24 00:00:00",
  "totals": {
    "12m": {
      "monetary": 0.0,
      "inkind": 0.0,
      "combined": 0.0,
      "payment_count": 0,
      "donor_count": 0,
      "mp_count": 0
    },
    "ytd": {
      "monetary": 0.0,
      "inkind": 0.0,
      "combined": 0.0,
      "payment_count": 0,
      "donor_count": 0,
      "mp_count": 0
    },
    "2025": {
      "monetary": 0.0,
      "inkind": 0.0,
      "combined": 0.0,
      "payment_count": 0,
      "donor_count": 0,
      "mp_count": 0
    },
    "2024": {
      "monetary": 0.0,
      "inkind": 0.0,
      "combined": 0.0,
      "payment_count": 0,
      "donor_count": 0,
      "mp_count": 0
    },
    "since_election": {
      "monetary": 0.0,
      "inkind": 0.0,
      "combined": 0.0,
      "payment_count": 0,
      "donor_count": 0,
      "mp_count": 0
    },
    "all_time": {
      "monetary": 0.0,
      "inkind": 0.0,
      "combined": 0.0,
      "payment_count": 0,
      "donor_count": 0,
      "mp_count": 0
    }
  },
  "officers": [
    {
      "appg_slug": "leasehold-and-commonhold-reform",
      "mnis_id": 4418,
      "name": "Justin Madders",
      "canon_name": "Justin Madders",
      "officer_role": "Chair & Registered Contact",
      "is_officer": 1,
      "member_type": "mp",
      "last_updated": "2026-02-23 00:00:00",
      "url_source": "https://publications.parliament.uk/pa/cm/cmallparty/260223/leasehold-and-commonhold-reform.htm",
      "removed": null
    },
    {
      "appg_slug": "leasehold-and-commonhold-reform",
      "mnis_id": 3682,
      "name": "Lord Truscott",
      "canon_name": "Lord Truscott",
      "officer_role": "Co-Chair",
      "is_officer": 1,
      "member_type": "lord",
      "last_updated": "2026-02-23 00:00:00",
      "url_source": "https://publications.parliament.uk/pa/cm/cmallparty/260223/leasehold-and-commonhold-reform.htm",
      "removed": null
    },
    {
      "appg_slug": "leasehold-and-commonhold-reform",
      "mnis_id": 5343,
      "name": "Mr Joshua Reynolds",
      "canon_name": "Joshua Reynolds",
      "officer_role": "Co-Chair",
      "is_officer": 1,
      "member_type": "mp",
      "last_updated": "2026-02-23 00:00:00",
      "url_source": "https://publications.parliament.uk/pa/cm/cmallparty/260223/leasehold-and-commonhold-reform.htm",
      "removed": null
    },
    {
      "appg_slug": "leasehold-and-commonhold-reform",
      "mnis_id": 4679,
      "name": "Neil O'Brien",
      "canon_name": "Neil O'Brien",
      "officer_role": "Co-Chair",
      "is_officer": 1,
      "member_type": "mp",
      "last_updated": "2026-02-23 00:00:00",
      "url_source": "https://publications.parliament.uk/pa/cm/cmallparty/260223/leasehold-and-commonhold-reform.htm",
      "removed": null
    }
  ],
  "members": [
    {
      "appg_slug": "leasehold-and-commonhold-reform",
      "mnis_id": 4418,
      "name": "Justin Madders",
      "canon_name": "Justin Madders",
      "officer_role": "Chair & Registered Contact",
      "is_officer": 1,
      "member_type": "mp",
      "last_updated": "2026-02-23 00:00:00",
      "url_source": "https://publications.parliament.uk/pa/cm/cmallparty/260223/leasehold-and-commonhold-reform.htm",
      "removed": null
    },
    {
      "appg_slug": "leasehold-and-commonhold-reform",
      "mnis_id": 3682,
      "name": "Lord Truscott",
      "canon_name": "Lord Truscott",
      "officer_role": "Co-Chair",
      "is_officer": 1,
      "member_type": "lord",
      "last_updated": "2026-02-23 00:00:00",
      "url_source": "https://publications.parliament.uk/pa/cm/cmallparty/260223/leasehold-and-commonhold-reform.htm",
      "removed": null
    },
    {
      "appg_slug": "leasehold-and-commonhold-reform",
      "mnis_id": 5343,
      "name": "Mr Joshua Reynolds",
      "canon_name": "Joshua Reynolds",
      "officer_role": "Co-Chair",
      "is_officer": 1,
      "member_type": "mp",
      "last_updated": "2026-02-23 00:00:00",
      "url_source": "https://publications.parliament.uk/pa/cm/cmallparty/260223/leasehold-and-commonhold-reform.htm",
      "removed": null
    },
    {
      "appg_slug": "leasehold-and-commonhold-reform",
      "mnis_id": 4679,
      "name": "Neil O'Brien",
      "canon_name": "Neil O'Brien",
      "officer_role": "Co-Chair",
      "is_officer": 1,
      "member_type": "mp",
      "last_updated": "2026-02-23 00:00:00",
      "url_source": "https://publications.parliament.uk/pa/cm/cmallparty/260223/leasehold-and-commonhold-reform.htm",
      "removed": null
    }
  ],
  "payments": []
}
