{
  "id": 269,
  "name": "The Co-operative Legal Services Limited",
  "address": "Aztec Centre, Aztec West, Almondsbury, Bristol, B232 4SD",
  "nature_of_business": "Solicitor",
  "donor_status": null,
  "is_private_individual": false,
  "totals": {
    "12m": {
      "monetary": 0.0,
      "inkind": 0.0,
      "combined": 0.0,
      "payment_count": 0,
      "donor_count": 0,
      "mp_count": 0
    },
    "ytd": {
      "monetary": 0.0,
      "inkind": 0.0,
      "combined": 0.0,
      "payment_count": 0,
      "donor_count": 0,
      "mp_count": 0
    },
    "2025": {
      "monetary": 5250.0,
      "inkind": 0.0,
      "combined": 5250.0,
      "payment_count": 3,
      "donor_count": 1,
      "mp_count": 1
    },
    "2024": {
      "monetary": 0.0,
      "inkind": 0.0,
      "combined": 0.0,
      "payment_count": 0,
      "donor_count": 0,
      "mp_count": 0
    },
    "since_election": {
      "monetary": 5250.0,
      "inkind": 0.0,
      "combined": 5250.0,
      "payment_count": 3,
      "donor_count": 1,
      "mp_count": 1
    },
    "all_time": {
      "monetary": 5250.0,
      "inkind": 0.0,
      "combined": 5250.0,
      "payment_count": 3,
      "donor_count": 1,
      "mp_count": 1
    }
  },
  "trend_12m": [
    0,
    0,
    0,
    0,
    0,
    0,
    0,
    0,
    0,
    0,
    0,
    0
  ],
  "payments": [
    {
      "id": 12077,
      "date": "2025-03-25",
      "category": "1.1",
      "member_id": 5197,
      "member_name": "Dr Neil Shastri-Hurst",
      "payer_id": 269,
      "payer_name": "The Co-operative Legal Services Limited",
      "amount": 2750.0,
      "payment_type": "Monetary",
      "is_regular": false,
      "period": null,
      "start_date": null,
      "end_date": null,
      "is_sole_beneficiary": true,
      "is_donated": false,
      "donated_to": null,
      "is_ultimate_payer_override": true,
      "is_confidential_payer": false,
      "appg_slug": null,
      "appg_name": null,
      "source_url": "https://members.parliament.uk/member/5197/registeredinterests?categoryId=1",
      "summary": "Payment received on 25 March 2025 - £2,750.00",
      "description": null
    },
    {
      "id": 12078,
      "date": "2025-03-25",
      "category": "1.1",
      "member_id": 5197,
      "member_name": "Dr Neil Shastri-Hurst",
      "payer_id": 269,
      "payer_name": "The Co-operative Legal Services Limited",
      "amount": 1600.0,
      "payment_type": "Monetary",
      "is_regular": false,
      "period": null,
      "start_date": null,
      "end_date": null,
      "is_sole_beneficiary": true,
      "is_donated": false,
      "donated_to": null,
      "is_ultimate_payer_override": true,
      "is_confidential_payer": false,
      "appg_slug": null,
      "appg_name": null,
      "source_url": "https://members.parliament.uk/member/5197/registeredinterests?categoryId=1",
      "summary": "Payment received on 25 March 2025 - £1,600.00",
      "description": null
    },
    {
      "id": 12079,
      "date": "2025-03-25",
      "category": "1.1",
      "member_id": 5197,
      "member_name": "Dr Neil Shastri-Hurst",
      "payer_id": 269,
      "payer_name": "The Co-operative Legal Services Limited",
      "amount": 900.0,
      "payment_type": "Monetary",
      "is_regular": false,
      "period": null,
      "start_date": null,
      "end_date": null,
      "is_sole_beneficiary": true,
      "is_donated": false,
      "donated_to": null,
      "is_ultimate_payer_override": true,
      "is_confidential_payer": false,
      "appg_slug": null,
      "appg_name": null,
      "source_url": "https://members.parliament.uk/member/5197/registeredinterests?categoryId=1",
      "summary": "Payment received on 25 March 2025 - £900.00",
      "description": null
    }
  ]
}
